{
  "_class": "shapeGroup",
  "clippingMaskMode": 0,
  "do_objectID": "7A581627-5A0A-460A-9554-ACC6B25A0662",
  "exportOptions": {
    "_class": "exportOptions",
    "exportFormats": [
    ],
    "includedLayerIds": [
    ],
    "layerOptions": 0,
    "shouldTrim": false
  },
  "frame": {
    "_class": "rect",
    "constrainProportions": false,
    "height": 567,
    "width": 3,
    "x": 16,
    "y": 0
  },
  "hasClickThrough": false,
  "hasClippingMask": false,
  "isFlippedHorizontal": false,
  "isFlippedVertical": false,
  "isLocked": false,
  "isVisible": true,
  "layerListExpandedType": 0,
  "layers": [
    {
      "class": "shapePath",
      "id": "26B16130-8ACE-41D4-AD67-6F65CD1E9659"
    }
  ],
  "name": "Shape",
  "nameIsFixed": false,
  "resizingConstraint": 63,
  "resizingType": 0,
  "rotation": 0,
  "shouldBreakMaskChain": false,
  "style": {
    "sharedObjectID": "789D2459-20D3-4883-9054-6928DF9190EB"
  },
  "windingRule": 1
}